tonalite/__init__.py
tonalite/cache.py
tonalite/config.py
tonalite/core.py
tonalite/data.py
tonalite/dataclasses.py
tonalite/exceptions.py
tonalite/frozen_dict.py
tonalite/py.typed
tonalite/types.py
tonalite-1.8.4.dist-info/LICENSE
tonalite-1.8.4.dist-info/METADATA
tonalite-1.8.4.dist-info/WHEEL
tonalite-1.8.4.dist-info/top_level.txt
tonalite-1.8.4.dist-info/RECORD
